hdfio/__init__.py
hdfio/dict_io.py
hdfio/json_io.py
hdfio/mat_io.py
hdfio-0.3.0.dist-info/LICENSE
hdfio-0.3.0.dist-info/METADATA
hdfio-0.3.0.dist-info/WHEEL
hdfio-0.3.0.dist-info/top_level.txt
hdfio-0.3.0.dist-info/RECORD
