Metadata-Version: 2.1
Name: hdfio
Version: 0.3.0
Summary: All the useful python I/O utility functions for HDF5 files
Home-page: https://github.com/RealPolitiX/hdfio
Author: R. Patrick Xian, others
Author-email: 
License: MIT
Download-URL: https://github.com/RealPolitiX/hdfio/tarball/0.3.0
Platform: UNKNOWN
Classifier: Development Status :: 3 - Alpha
Classifier: Intended Audience :: Developers
Classifier: Programming Language :: Python :: 3
Requires-Dist: numpy
Requires-Dist: h5py
Requires-Dist: silx
Requires-Dist: deepdish
Requires-Dist: h5io
